Workbook
Name Acreditado_Obs1: 'Tarifas (2)'!$C$7:$C$17
Name Acreditado_Obs1: Tarifas!$C$7:$C$25
Name No_Acreditado: 'Tarifas (2)'!$C$18:$C$105
Name No_Acreditado: Tarifas!$C$26:$C$107

Sheet Cotización V009
A1: UNIVERSIDAD SANTIAGO DE CALI DIRECCIÓN GENERAL DE LABORATORIOS LABORATORIO DE METROLOGÍA Calle 5ª Carrera 62 Campus Pampalinda Bloque 4 Piso 1 Laboratorio 4129 PBX: 5183000 Ext. 9093 E-mail: comercialmetrologia@usc.edu.co
A2: COTIZACIÓN DE SERVICIOS DE CALIBRACIÓN
A3: R-CM003 / Versión 9 2024/09/17
A4: Tenemos el gusto de presentarle nuestra propuesta económica para la calibración de equipos
A5: No. Cotización: | B5: 26-1241A
A6: Fecha: | B6: 46056
A7: Empresa: | B7: Aldeas Infantiles | E7: Nit: | F7: N.I
A8: Ciudad | B8: Cali | E8: Teléfono: | F8: 300 2584998
A9: Contacto: | B9: David Rendon | E9: Email: | F9: david.rendon@aldeasinfantiles.org.co
A11: Equipo / Número de puntos | B11: Tipo de servicio | C11: Magnitud | E11: Norma / Guía Técnica | F11: Cantidad | G11: Valor Unitario | H11: Valor Total
A12: Termómetros digitales con sensor termopar, RTD, termómetros digitales con sonda o punzón - 30 °C ≤ t ≤ 150 °C (Incluye 3 puntos de calibración) | B12: Acreditado_Obs1 | C12: =IF(B12="","",VLOOKUP(A12,Tarifas!$C$7:$G$108,2,FALSE)) -> Temperatura | E12: =IF(B12="","",VLOOKUP(A12,Tarifas!$C$7:$E$108,3,FALSE)) -> Procedimiento TH-001 para la calibración de termómetros digitales (de lectura directa) por comparación, Centro Español de Metrología, edición digital 2.2021 | F12: 4 | G12: =IF(B12="","",VLOOKUP(A12,Tarifas!$C$7:$H$107,6,FALSE)) -> 156600 | H12: =IF(B12="","",G12*F12) -> 626400
C13: =IF(B13="","",VLOOKUP(A13,Tarifas!$C$8:$G$107,2,FALSE)) | E13: =IF(B13="","",VLOOKUP(A13,Tarifas!$C$7:$E$108,3,FALSE)) | G13: =IF(B13="","",VLOOKUP(A13,Tarifas!$C$6:$H$107,6,FALSE)) | H13: =IF(B13="","",G13*F13)
C14: =IF(B14="","",VLOOKUP(A14,Tarifas!$C$8:$G$107,2,FALSE)) | E14: =IF(B14="","",VLOOKUP(A14,Tarifas!$C$7:$E$108,3,FALSE)) | G14: =IF(B14="","",VLOOKUP(A14,Tarifas!$C$6:$H$107,6,FALSE)) | H14: =IF(B14="","",G14*F14)
C15: =IF(B15="","",VLOOKUP(A15,Tarifas!$C$8:$G$107,2,FALSE)) | E15: =IF(B15="","",VLOOKUP(A15,Tarifas!$C$7:$E$108,3,FALSE)) | G15: =IF(B15="","",VLOOKUP(A15,Tarifas!$C$6:$H$107,6,FALSE)) | H15: =IF(B15="","",G15*F15)
C16: =IF(B16="","",VLOOKUP(A16,Tarifas!$C$8:$G$107,2,FALSE)) | E16: =IF(B16="","",VLOOKUP(A16,Tarifas!$C$7:$E$108,3,FALSE)) | G16: =IF(B16="","",VLOOKUP(A16,Tarifas!$C$6:$H$107,6,FALSE)) | H16: =IF(B16="","",G16*F16)
C17: =IF(B17="","",VLOOKUP(A17,Tarifas!$C$8:$G$107,2,FALSE)) | E17: =IF(B17="","",VLOOKUP(A17,Tarifas!$C$7:$E$108,3,FALSE)) | G17: =IF(B17="","",VLOOKUP(A17,Tarifas!$C$6:$H$107,6,FALSE)) | H17: =IF(B17="","",G17*F17)
C18: =IF(B18="","",VLOOKUP(A18,Tarifas!$C$8:$G$107,2,FALSE)) | E18: =IF(B18="","",VLOOKUP(A18,Tarifas!$C$7:$E$108,3,FALSE)) | G18: =IF(B18="","",VLOOKUP(A18,Tarifas!$C$6:$H$107,6,FALSE)) | H18: =IF(B18="","",G18*F18)
C19: =IF(B19="","",VLOOKUP(A19,Tarifas!$C$8:$G$107,2,FALSE)) | E19: =IF(B19="","",VLOOKUP(A19,Tarifas!$C$7:$E$108,3,FALSE)) | G19: =IF(B19="","",VLOOKUP(A19,Tarifas!$C$6:$H$107,6,FALSE)) | H19: =IF(B19="","",G19*F19)
C20: =IF(B20="","",VLOOKUP(A20,Tarifas!$C$8:$G$107,2,FALSE)) | E20: =IF(B20="","",VLOOKUP(A20,Tarifas!$C$7:$E$108,3,FALSE)) | G20: =IF(B20="","",VLOOKUP(A20,Tarifas!$C$6:$H$107,6,FALSE)) | H20: =IF(B20="","",G20*F20)
C21: =IF(B21="","",VLOOKUP(A21,Tarifas!$C$8:$G$107,2,FALSE)) | E21: =IF(B21="","",VLOOKUP(A21,Tarifas!$C$7:$E$108,3,FALSE)) | G21: =IF(B21="","",VLOOKUP(A21,Tarifas!$C$6:$H$107,6,FALSE)) | H21: =IF(B21="","",G21*F21)
C22: =IF(B22="","",VLOOKUP(A22,Tarifas!$C$8:$G$107,2,FALSE)) | E22: =IF(B22="","",VLOOKUP(A22,Tarifas!$C$7:$E$108,3,FALSE)) | G22: =IF(B22="","",VLOOKUP(A22,Tarifas!$C$6:$H$107,6,FALSE)) | H22: =IF(B22="","",G22*F22)
C23: =IF(B23="","",VLOOKUP(A23,Tarifas!$C$8:$G$107,2,FALSE)) | E23: =IF(B23="","",VLOOKUP(A23,Tarifas!$C$7:$E$108,3,FALSE)) | G23: =IF(B23="","",VLOOKUP(A23,Tarifas!$C$6:$H$107,6,FALSE)) | H23: =IF(B23="","",G23*F23)
C24: =IF(B24="","",VLOOKUP(A24,Tarifas!$C$8:$G$107,2,FALSE)) | E24: =IF(B24="","",VLOOKUP(A24,Tarifas!$C$7:$E$108,3,FALSE)) | G24: =IF(B24="","",VLOOKUP(A24,Tarifas!$C$6:$H$107,6,FALSE)) | H24: =IF(B24="","",G24*F24)
... C47: =IF(B47="","",VLOOKUP(A47,Tarifas!$C$8:$G$107,2,FALSE)) | E47: =IF(B47="","",VLOOKUP(A47,Tarifas!$C$7:$E$108,3,FALSE)) | G47: =IF(B47="","",VLOOKUP(A47,Tarifas!$C$6:$H$107,6,FALSE)) | H47: =IF(B47="","",G47*F47)
E49: Total de Servicio | F49: =SUM(F12:F47) -> 4 | G49: =SUM(H12:H47) -> 626400
E50: Descuento (%) | H50: =G49*F50 -> 0 | L50: Método de pago: 60 Dias
E51: Viáticos | L51: Método de pago: 30 Dias
E52: TOTAL | H52: =G49-H50+F51 -> 626400 | L52: Método de pago: Contado
A54: Acreditado_Obs1: El laboratorio de Metrología de la universidad Santiago de Cali cuenta con acreditación ONAC vigente a la fecha, con código de acreditación 20-LAC-021, bajo la norma ISO/IEC17025:2017 en las magnitudes de Presion, Masa (Instrumentos de pesaje), Temperatura en inmersión, temperatura y Humedad en condiciones ambietales.
A56: Condiciones Comerciales y Técnicas
A57: Método de pago: 30 Dias
A58: Tener presente que: 1. El tiempo de validez de la oferta es de treinta (30) días. 2. El Laboratorio de Metrología de la Universidad Santiago de Cali NO realiza cobro de IVA. 3. Si la propuesta es aceptada, por favor enviar orden de Compra o aprobacion por escrito o cotización firmada por la persona a cargo del servicio (en caso de no manejar orden de compra), RUT actualizado (sí es cliente nuevo) y formato orden de trabajo R-CM005 diligenciado. 4. La programación del servicio de calibración en sitio y laboratorio permanente dependerá de la disponibilidad del laboratorio, es decir que según la cantidad de servicios que se tengan agendados y estén en línea de llegada para calibración, las fechasde las calibraciones están sujetas a cambios, por actividades que impidan el normal funcionamiento del laboratorio, inconvenientes presentados durante el servicio o acontecimientos externos (terremotos, atentados, robos entre otros). 5. Los viáticos relacionan traslado de equipos patrones, personal técnico, alimentación y hospedaje. Estos están sujetos a cambios, por novedades presentadas en la prestación del mismo (como la disponibilidad de equipos, estado del equipo), para calibraciones en sitio solo bajo el proceso de calibración se podrá determinar si el instrumento es apto , en caso contrario se le informará al cliente. 6. El Punto Adicional en Temperatura y Humedad tiene un costo de $ 55.000.
A59: Nota A: El formato orden de trabajo R-CM005 debe ser diligenciado, para poder dar inicio al proceso de calibración.
A60: Nota B: Por favor tener en cuenta que el pago acordado dentro de la cotización debe ser cumplido, si usted no está de acuerdo antes de realizar el servicio deberá informar por escrito, de lo contrario cualquier retraso generará un interés por mora del 2,16% sobre el total de la factura.
A61: Nota C: El Laboratorio No realiza mantenimiento, ajuste y desmonte de equipos.
A62: Nota D: El plazo de entrega para el instrumento es de cinco (5) días hábiles, contados a partir de la recepción del equipo y del formato orden de trabajo R-CM005 debidamente diligenciado. Este tiempo puede variar teniendo en cuenta la cantidad de servicios que se tengan agendados previamente, la hora de llegada de los instrumentos a nuestras instalaciones y que los equipos deben contar con las óptimas condiciones de funcionamiento, deben incluir los accesorios (cables, sensores, transductores, baterías, software, entre otros) Para los equipos de tempertaratura ambiental y humedad el tiempo para la entrega sera de (8) dias habiles.
A63: Nota E: El certificado o reporte de resultados será entregado en un plazo de Tres (3) días hábiles, después de realizadas las calibraciones y verificada la cancelación del servicio.
A64: Nota G: Para instrumentos de pesaje de funcionamiento no automático, con un solo punto de apoyo o que su plataforma no permita la ubicación de las pesas, no se le realizara la prueba de excentricidad.
A65: Nota H: Los certificados de calibración serán enviados al correo que se indique en el formato orden de trabajo R-CM005, con firma digital y en formato (PDF).
A66: Nota I: En caso de que no se especifique los puntos de calibración en las magnitudes de Masa y presión el laboratorio de Metrología de la Universidad Santiago de Cali podrá realizar la asignación de acuerdo a : 1. Magnitud de Presión: Se establece al menos 5 puntos de calibración para la magnitud de presión. Estos puntos estarán regularmente espaciados desde el 10% hasta el 100% del intervalo de medición del equipo. 2. Magnitud de Masa: (instrumentos de pesaje), se establecerán 10 puntos de calibración. Estos puntos abarcarán desde la carga mínima hasta la carga máxima especificada para los instrumentos sujetos a calibración.
... A72: La Universidad Santiago de Cali, está comprometida con la gestión frente a las solicitudes (peticiones, quejas, reclamos y/o sugerencias) de los usuarios, garantizando respuestas oportunas y efectivas, dando cumplimiento a los requisitos legales y a los principios de orientación para su tratamiento, los cuales permiten visibilidad, accesibilidad, respuesta diligente, tratamiento equitativo, objetivo e imparcial , acceso al proceso de tratamiento de las solicitudes sin costo para el reclamante, confidencialidad, enfoque al cliente, responsabilidad y mejora continua, transformando el sistema de gestión de las peticiones, quejas , reclamos y sugerencias (PQRS), en una herramienta para el control de los servicios y procesos desarrollados por la institución.
A73: Enlace para el ingreso al sistema de Peticiones, Quejas, Reclamos y Sugerencias (PQRS) | F73: https://pqrs.usc.edu.co/
A74: Calibración en laboratorio
A75: El cliente debe hacerse cargo de transportar los equipos hasta las instalaciones del Laboratorio de Metrología de la Universidad Santiago de Cali, con dirección Calle 5 No 62-00, Bloque 4 Piso 1 Sede Pampalinda. En los horarios de atención de Lunes a Viernes de 8:00 am a 11:00 am y de 3:00 pm a 5:00 pm, sabados de 8 am a 12 am.
A76: Calibración en sitio
A77: Para calibraciones en sitio, se debe coordinar con antelación el servicio, con el propósito de tener acceso a los equipos programados en las fechas y horarios acordados, verificar que los equipos cuenten con mantenimiento preventivo y estar disponibles en las áreas de trabajo acordadas. El área de trabajo debe contar con buenas condiciones de aseo y desinfección (para áreas clínicas), contar con superficies planas para la ejecución el trabajo (mesas, escritorios, etc.), buena iluminación y ventilación (de acuerdo al procedimiento de calibración, se solicitará condiciones ambientales controladas). Contar con tomas eléctricos preferiblemente con energía regulada, se debe restringir el acceso a otras personas mientras se realiza el servicio de calibración, es decir que solamente debe estar el personal encargado del equipo bajo prueba. El personal del laboratorio de Metrología de la Universidad Santiago de Cali, no desinstalará o instalará equipos de las bases de trabajo, al igual que no manipulará equipos a los cuales esté conectado algún paciente.
A78: Confidencialidad
A79: La información obtenida o creada durante la realización de actividades del Laboratorio de Metrología de la Universidad Santiago de Cali es confidencial entre el cliente y/o usuario final y el laboratorio. Cuando los entes legales o de control requieran información obtenida o creada durante la realización de actividades del laboratorio, esta será entregada y el cliente será notificado salvo cuando la ley lo prohíba. La información producto de servicio estará disponible en los procesos de evaluación por parte del ente acreditador y en procesos de auditorias internas, como un insumo para evaluar la conformidad. Siempre garantizando la confidencialidad de los resultados.
A80: Política de imparcialidad
A81: El Laboratorio de Metrología de la Universidad Santiago de Cali declara que todas las actividades efectuadas en el proceso metrológico están desarrolladas bajo principios de Independencia, Imparcialidad y Confidencialidad, de modo que se asegura que las actividades de calibración de equipos e instrumentos y la emisión de certificados están basadas en los resultados obtenidos a partir de los equipos patrones, la aplicación de los procedimientos pertinentes, la ejecución de las actividades por el personal competente autorizado, el registro real de los datos de condiciones ambientales, fecha de calibración y emisión de certificado, ítem bajo prueba , lugar de ejecución del servicio y equipo patrón empleado. Por lo anterior la dirección técnica y el personal están libres de cualquier presión o influencia indebida, interna o externa, comercial, financiera o de otro tipo que se constituya como conflicto de Interés, que pueda perjudicar la calidad y validez de los resultados.
A83: Departamento Comercial
A84: Cel. 3148901580
A85: Tel. 5183000 ext. 9092 9093

Sheet Tarifas
C1: UNIVERSIDAD SANTIAGO DE CALI DIRECCIÓN GENERAL DE LABORATORIOS Calle 5 Carrera 62 Campus Pampalinda LABORATORIO DE METROLOGÍA Bloque 4 Piso 1 Laboratorio 4129. PBX: 5183000 Ext. 9093- 9092 Celular: 314 8901580 E-mail: labmetrologia@usc.edu.co / comercialmetrologia@usc.edu.co
C5: TARIFAS
C6: EQUIPO | D6: MAGNITUD A CALIBRAR | E6: MÉTODO/ PROCEDIMIENTO | F6: # | G6: PRECIO UNITARIO 2025 | H6: PRECIO UNITARIO 2026 | I6: PRECIO AL POR MAYOR 2025 (15%)
B7: HUMEDAD | C7: Termohigrómetros / Analógicos 20 %hr ≤ hr ≤ 80 %hr 10 °C ≤ t ≤ 40 °C (Incluye 3 puntos de calibración una variable) | D7: Temperatura (Ambiente) - Humedad relativa | E7: P-CL034 Procedimiento interno Calibración de termohigrómetros analógicos v004 de 2021-08-24 | F7: 1 | G7: 155000 | H7: =G7+(G7*0.08) -> 167400 | I7: =H7-(H7*0.15) -> 142290
C8: Termohigrómetros / Digitales 20 %hr ≤ hr ≤ 80 %hr 10 °C ≤ t ≤ 40 °C (Incluye 3 puntos de calibración por variable) | D8: Temperatura (Ambiente) - Humedad relativa | E8: Procedimiento TH-007 para calibración de medidores de condiciones ambientales de temperatura y humedad en aire, Centro Español de Metrología, edición digital 1. 2021 | F8: 2 | G8: 155000 | H8: =G8+(G8*0.08) -> 167400 | I8: =H8-(H8*0.15) -> 142290
C9: Punto adicional Termohigrómetros / Analógicos 20 %hr ≤ hr ≤ 80 %hr 10 °C ≤ t ≤ 40 °C | D9: Temperatura (Ambiente) - Humedad relativa | E9: P-CL034 Procedimiento interno Calibración de termohigrómetros analógicos v004 de 2021-08-24 | F9: 3 | G9: 50000 | H9: 50000 | I9: =H9-(H9*0.15) -> 42500
C10: Punto adicional Termohigrómetros / Digitales 20 %hr ≤ hr ≤ 80 %hr 10 °C ≤ t ≤ 40 °C | D10: Temperatura (Ambiente) - Humedad relativa | E10: Procedimiento TH-007 para calibración de medidores de condiciones ambientales de temperatura y humedad en aire, Centro Español de Metrología, edición digital 1. 2021 | F10: 4 | G10: 50000 | H10: 50000 | I10: =H10-(H10*0.15) -> 42500
B11: TEMPERATURA | C11: Punto adicional Termómetros digitales con sensor termopar, RTD, termómetros digitales con sonda o punzón - 30 °C ≤ t ≤ 150 °C | D11: Temperatura | E11: Procedimiento TH-001 para la calibración de termómetros digitales (de lectura directa) por comparación, Centro Español de Metrología, edición digital 2.2021 | F11: 5 | G11: 50000 | H11: 50000 | I11: =H11-(H11*0.15) -> 42500
C12: Punto adicional Termómetros de indicación analógica sonda o punzón - 30 °C ≤ t ≤ 150 °C | D12: Temperatura | E12: Nordtest Method Thermometer, contact direct reading: Calibration NT VVS 103 Approved 1994-09. | F12: 6 | G12: 50000 | H12: 50000 | I12: =H12-(H12*0.15) -> 42500
C13: Termómetros digitales con sensor termopar, RTD, termómetros digitales con sonda o punzón - 30 °C ≤ t ≤ 150 °C (Incluye 3 puntos de calibración) | D13: Temperatura | E13: Procedimiento TH-001 para la calibración de termómetros digitales (de lectura directa) por comparación, Centro Español de Metrología, edición digital 2.2021 | F13: 7 | G13: 145000 | H13: =G13+(G13*0.08) -> 156600 | I13: =H13-(H13*0.15) -> 133110
C14: Termómetros de indicación analógica sonda o punzón - 30 °C ≤ t ≤ 150 °C (3 puntos de calibración) | D14: Temperatura | E14: Nordtest Method Thermometer, contact direct reading: Calibration NT VVS 103 Approved 1994-09. | F14: 8 | G14: 135000 | H14: =G14+(G14*0.08) -> 145800 | I14: =H14-(H14*0.15) -> 123930
B15: PRESION | C15: Manómetros analógicos y digitales Clase de exactitud ≥ 0,5 % de escala completa. (-10 psi ≤ p ≤ 0 psi) | D15: Presión | E15: Procedimiento ME-003 para la calibración de manómetros, vacuómetros y manovacuómetros, Centro Español de Metrologia, Edición Digital 3, 2019. | F15: 9 | G15: 105000 | H15: 105000 | I15: =H15-(H15*0.15) -> 89250
C16: Manómetros analógicos y digitales Clase de exactitud ≥ 0,05 % de escala completa. (0 psi < p ≤ 50 psi) | D16: Presión | E16: Procedimiento ME-003 para la calibración de manómetros, vacuómetros y manovacuómetros, Centro Español de Metrologia, Edición Digital 3, 2019. | F16: 10 | G16: 105000 | H16: 105000 | I16: =H16-(H16*0.15) -> 89250
C17: Manómetros analógicos y digitales Clase de exactitud ≥ 0,05 % de escala completa. (50 psi < p ≤ 300 psi) | D17: Presión | E17: Procedimiento ME-003 para la calibración de manómetros, vacuómetros y manovacuómetros, Centro Español de Metrologia, Edición Digital 3, 2019. | F17: 11 | G17: 105000 | H17: 105000 | I17: =H17-(H17*0.15) -> 89250
C18: Manómetros analógicos y digitales Clase de exactitud ≥ 0,05 % de escala completa. (300 psi < p ≤ 1000 psi) | D18: Presión | E18: Procedimiento ME-003 para la calibración de manómetros, vacuómetros y manovacuómetros, Centro Español de Metrologia, Edición Digital 3, 2019. | F18: 12 | G18: 150000 | H18: 105000 | I18: =H18-(H18*0.15) -> 89250
C19: Esfigmomanómetros mecánicos no invasivos analógicos 0 kPa ≤ p ≤ 40 kPa (0 mmHg ≤ p ≤ 300 mmHg) (incluye 7 puntos de calibración) | D19: Presión | E19: OIML R148-2 Non-invasive non-automated sphygmomanometers, Edition 2020, Numerales 1 y 10. | F19: 13 | G19: 95000 | H19: 95000 | I19: =H19-(H19*0.15) -> 80750
B20: MASA | C20: Instrumentos de pesaje de funcionamiento no automático con d ≥ 0,01 mg 0 g < m ≤ 220 g (incluye 11 puntos de calibración) | D20: Masa | E20: Guía para la calibración de instrumentos para pesar de funcionamiento no automático, SIM MWG7/cg-01/v.00. 2009. | F20: 14 | G20: 225000 | H20: =G20+(G20*0.08) -> 243000 | I20: =H20-(H20*0.15) -> 206550
C21: Instrumentos de pesaje de funcionamiento no automático con d ≥ 10 mg 220 g < m ≤ 5000 g (incluye 11 puntos de calibración) | D21: Masa | E21: Guía para la calibración de instrumentos para pesar de funcionamiento no automático, SIM MWG7/cg-01/v.00. 2009. | F21: 15 | G21: 188000 | H21: =G21+(G21*0.08) -> 203040 | I21: =H21-(H21*0.15) -> 172584
C22: Instrumentos de pesaje de funcionamiento no automático con d ≥ 0,1 g 5000 g < m ≤ 34 kg (incluye 11 puntos de calibración) | D22: Masa | E22: Guía para la calibración de instrumentos para pesar de funcionamiento no automático, SIM MWG7/cg-01/v.00.2009 | F22: 16 | G22: 188000 | H22: =G22+(G22*0.08) -> 203040 | I22: =H22-(H22*0.15) -> 172584
C23: Instrumentos de pesaje de funcionamiento no automático con d ≥ 10 g 34 kg < m ≤ 150 kg (incluye 11 puntos de calibración) | D23: Masa | E23: Guía para la calibración de instrumentos para pesar de funcionamiento no automático, SIM MWG7/cg-01/v.00.2009 | F23: 17 | G23: 188000 | H23: =G23+(G23*0.1) -> 206800 | I23: =H23-(H23*0.15) -> 175780
C24: Instrumentos de pesaje de funcionamiento no automático con d ≥ 50 g 150 kg < m ≤ 500 kg (incluye 11 puntos de calibración) | D24: Masa | E24: Guía para la calibración de instrumentos para pesar de funcionamiento no automático, SIM MWG7/cg-01/v.00.2009 | F24: 18 | G24: 188000 | H24: =G24+(G24*0.15) -> 216200 | I24: =H24-(H24*0.15) -> 183770
C25: Instrumentos de pesaje de funcionamiento no automático con d ≥ 0,1 kg 500 kg < m ≤ 1000 kg (incluye 11 puntos de calibración) | D25: Masa | E25: Guía para la calibración de instrumentos para pesar de funcionamiento no automático, SIM MWG7/cg-01/v.00.2009 | F25: 19 | G25: Por definir | H25: =G25+(G25*0.08) -> #VALUE! | I25: =H25-(H25*0.15) -> #VALUE!
B26: No Acreditado | C26: Agitadores de Mazzini | D26: Velocidad Angular (RPM) | E26: Procedimiento Interno | F26: 20 | G26: 98000 | H26: =G26+(G26*0.05) -> 102900 | I26: =H26-(H26*0.15) -> 87465
C27: Arco En C | D27: kV, tiempo, kV emitido | E27: Procedimiento Interno | F27: 21 | G27: 445000 | H27: =G27+(G27*0.05) -> 467250 | I27: =H27-(H27*0.15) -> 397162.5
C28: Aspiradores De Vacío (Succionador) | D28: Presión Negativa. | E28: Procedimiento Interno | F28: 22 | G28: 115000 | H28: =G28+(G28*0.05) -> 120750 | I28: =H28-(H28*0.15) -> 102637.5
C29: Pulsoxímetro O Monitor De Saturación De Oxigeno | D29: % SpO2 - Frecuencia Cardíaca. | E29: Procedimiento Interno | F29: 23 | G29: 82000 | H29: =G29+(G29*0.05) -> 86100 | I29: =H29-(H29*0.15) -> 73185
C30: Banda de esfuerzo | D30: Frecuencia Cardíaca - NIBP- % SpO2 | E30: Procedimiento Interno | F30: 24 | G30: 120000 | H30: =G30+(G30*0.05) -> 126000 | I30: =H30-(H30*0.15) -> 107100
C31: Baño Serológico - Baño de Maria | D31: Temperatura (4 puntos) | E31: Procedimiento Interno | F31: 25 | G31: 110000 | H31: =G31+(G31*0.05) -> 115500 | I31: =H31-(H31*0.15) -> 98175
C32: Blender | D32: Concentración de O2 | E32: Procedimiento Interno | F32: 26 | G32: 110000 | H32: =G32+(G32*0.05) -> 115500 | I32: =H32-(H32*0.15) -> 98175
C33: Bomba de infusión | D33: Volumen - Flujo | E33: Procedimiento Interno | F33: 27 | G33: 138000 | H33: =G33+(G33*0.05) -> 144900 | I33: =H33-(H33*0.15) -> 123165
C34: Calentador de Liquidos | D34: Temperatura | E34: Procedimiento Interno | F34: 28 | G34: 95000 | H34: =G34+(G34*0.05) -> 99750 | I34: =H34-(H34*0.15) -> 84787.5
C35: Calefactor de manta térmica | D35: Temperatura | E35: Procedimiento Interno | F35: 29 | G35: 95000 | H35: =G35+(G35*0.05) -> 99750 | I35: =H35-(H35*0.15) -> 84787.5
C36: Criostato | D36: Temperatura | E36: Procedimiento Interno | F36: 30 | G36: 225000 | H36: =G36+(G36*0.05) -> 236250 | I36: =H36-(H36*0.15) -> 200812.5
C37: Capnógrafo | D37: CO2 - %SpO2 | E37: Procedimiento Interno | F37: 31 | G37: 180000 | H37: =G37+(G37*0.05) -> 189000 | I37: =H37-(H37*0.15) -> 160650
C38: Amalgamador | D38: Revoluciones por minuto( RPM) | E38: Procedimiento Interno | F38: 32 | G38: 120000 | H38: =G38+(G38*0.05) -> 126000 | I38: =H38-(H38*0.15) -> 107100
... C70: Espirómetro | D70: Volumen - Flujo | E70: Procedimiento Interno | F70: 64 | G70: 180000 | H70: =G70+(G70*0.05) -> 189000 | I70: =H70-(H70*0.15) -> 160650
C71: Cuna De Calor Radiante | D71: Temperatura | E71: Procedimiento Interno | F71: 65 | G71: $ 172.500 | H71: =G71+(G71*0.05) -> 181125 | I71: =H71-(H71*0.15) -> 153956.25
C72: Lámparas De Fotocurado | D72: mW/cm2 | E72: Procedimiento Interno | F72: 66 | G72: 117000 | H72: =G72+(G72*0.05) -> 122850 | I72: =H72-(H72*0.15) -> 104422.5
C73: Lámpara De Fototerapia | D73: μw/Cm2 | E73: Procedimiento Interno | F73: 67 | G73: 140000 | H73: =G73+(G73*0.05) -> 147000 | I73: =H73-(H73*0.15) -> 124950
C74: Máquina De Anestesia (Sin Vaporizadores) (Incluido Ventilador) | D74: Volumen - Tiempo - Frecuencia - Presión – Flujo. | E74: Procedimiento Interno | F74: 68 | G74: 480000 | H74: =G74+(G74*0.05) -> 504000 | I74: =H74-(H74*0.15) -> 428400
C75: Marcapasos Externos | D75: Frecuencia, Sensibilidad ,Ancho De Pulso. | E75: Procedimiento Interno | F75: 69 | G75: 198000 | H75: =G75+(G75*0.05) -> 207900 | I75: =H75-(H75*0.15) -> 176715
C76: Monitor multiparamétrico (10 Variables) | D76: Frecuencia Cardíaca - %SpO2 - NIBP - Temperatura, Frecuencia Respiratoria-Gasto Cardíaco- Presión Invasiva (IBP) ,CO2, (8 a 10 Variables) | E76: Procedimiento Interno | F76: 70 | G76: 250000 | H76: =G76+(G76*0.05) -> 262500 | I76: =H76-(H76*0.15) -> 223125
C77: Monitor de Signos Vitales (De 3 a 5 Variables) | D77: Frecuencia , %SpO2, NIBP, Temperatura o Frecuencia respiratoria (3 a 5 Variables) | E77: Procedimiento Interno | F77: 71 | G77: 190000 | H77: =G77+(G77*0.05) -> 199500 | I77: =H77-(H77*0.15) -> 169575
C78: Monitor de Signos Vitales ( De 5 a 7 Variables) | D78: Frecuencia Cardíaca - %SpO2 - NIBP - Temperatura, Frecuencia Respiratoria, Presión Invasiva (IBP) ( 5 a 7 Variables) | E78: Procedimiento Interno | F78: 72 | G78: 230000 | H78: =G78+(G78*0.05) -> 241500 | I78: =H78-(H78*0.15) -> 205275
C79: Pulsiometro - Monitor de Oxígeno (Oximetro) | D79: %SpO2 | E79: Procedimiento Interno | F79: 73 | G79: 85000 | H79: =G79+(G79*0.05) -> 89250 | I79: =H79-(H79*0.15) -> 75862.5
C80: Monitor Fetal | D80: Fetocardia y Nivel de Contracción Uterina | E80: Procedimiento Interno | F80: 74 | G80: 226000 | H80: =G80+(G80*0.05) -> 237300 | I80: =H80-(H80*0.15) -> 201705
C81: Nevera Farmacéutica | D81: Servicio de validación a (nevera farmacéutica 1 puerta, muestreo por 24 horas, IQ, OQ PQ, 5 sensores temp, test de puerta abierta, test de desconexión, test de recuperación,) | E81: Validación | F81: 75 | G81: 360000 | H81: =G81+(G81*0.05) -> 378000 | I81: =H81-(H81*0.15) -> 321300
C82: Neumoinsuflador | D82: Flujo y Presión | E82: Procedimiento Interno | F82: 76 | G82: 178000 | H82: =G82+(G82*0.05) -> 186900 | I82: =H82-(H82*0.15) -> 158865
C83: Neumotaponador | D83: Presión | E83: Procedimiento Interno | F83: 77 | G83: 135000 | H83: =G83+(G83*0.05) -> 141750 | I83: =H83-(H83*0.15) -> 120487.5
... C107: Ventiladores Mecánicos de alta Frecuencia | D107: Volumen -Frecuencia Respiratoria -Presiónes- Flujo-Tiempo y FiO2 | E107: Procedimiento Interno | F107: 101 | G107: 240000 | H107: =G107+(G107*0.05) -> 252000 | I107: =H107-(H107*0.15) -> 214200

Sheet Control de cambios
J2: UNIVERSIDAD SANTIAGO DE CALI LABORATORIO DE METROLOGÍA
J5: Hoja para control de cambios
B9: Nombre | I9: : | J9: Formato de cotización
B10: Código | I10: : | J10: R-CM003
B12: N° Versión | E12: Fecha de cambio | J12: Descripción | X12: ¿Se realiza validación de la hoja de cálculo? | Y12: Observaciones | AH12: Aprobó
B13: 09 | E13: 45552 | J13: Se realiza modificación estableciendo la condición de acreditado según numeral 4.3.1 del RAC-3.0-03 versión 9. Se incluye cuadro para el control de cambios dentro del formato. | X13: No | Y13: N.A | AH13: Luis Miguel Burgos

Sheet Tarifas (2)
C1: UNIVERSIDAD SANTIAGO DE CALI DIRECCIÓN GENERAL DE LABORATORIOS Calle 5 Carrera 62 Campus Pampalinda LABORATORIO DE METROLOGÍA Bloque 4 Piso 1 Laboratorio 4129. PBX: 5183000 Ext. 9093- 9092 Celular: 314 8901580 E-mail: labmetrologia@usc.edu.co / comercialmetrologia@usc.edu.co
C5: TARIFAS
C6: EQUIPO | D6: MAGNITUD A CALIBRAR | E6: MÉTODO/ PROCEDIMIENTO | F6: # | G6: Precio unitario 2024 | H6: Precios al por mayor 2024
B7: HUMEDAD | C7: Termohigrómetros / Analógicos 30 %hr ≤ hr ≤ 80 %hr 10 °C ≤ t ≤ 35 °C (Incluye 3 puntos de calibración una variable) | D7: Temperatura (Ambiente) - Humedad relativa | E7: P-CL034 Procedimiento interno Calibración de termohigrómetros analógicos v004 de 2021-08-24 | F7: 1 | G7: 150000 | H7: 127500
C8: Termohigrómetros / Digitales 30 %hr ≤ hr ≤ 80 %hr 10 °C ≤ t ≤ 35 °C (Incluye 3 puntos de calibración por variable) | D8: Temperatura (Ambiente) - Humedad relativa | E8: Procedimiento TH-007 para calibración de medidores de condiciones ambientales de temperatura y humedad en aire, Centro Español de Metrología, Edición Digital 1. | F8: 2 | G8: 150000 | H8: 127500
B9: TEMPERATURA | C9: Termómetros digitales con sensor termopar, RTD, termómetros digitales con sonda o punzón - 30 °C ≤ t ≤ 150 °C (Incluye 3 puntos de calibración) | D9: Temperatura | E9: Procedimiento TH-001 para la calibración de termómetros digitales (de lectura directa) por comparación, Centro Español de Metrología, edición digital 2, 2019. | F9: 3 | G9: 140000 | H9: =G9-(G9*0.15) -> 119000
C10: Termómetros de indicación analógica sonda o punzón - 30 °C ≤ t ≤ 70 °C (3 puntos de calibración) | D10: Temperatura | E10: Nordtest Method Thermometer, contact direct reading: Calibration NT VVS 103 Approved 1994-09. | F10: 4 | G10: 130000 | H10: =G10-(G10*0.15) -> 110500
B11: PRESION | C11: Manómetros analógicos y digitales Clase de exactitud ≥ 1% de escala completa 0 kPa ≤ p ≤ 0,345 MPa (0 psi ≤ p ≤ 50 psi) (incluye 5 puntos de calibración) | D11: Presión | E11: Procedimiento ME-003 para la calibración de manómetros, vacuómetros y manovacuómetros, Centro Español de Metrologia, Edición Digital 3, 2019. | F11: 5 | G11: 100000 | H11: =G11-(G11*0.15) -> 85000
C12: Infusores de liquidos (Manómetro) Clase de exactitud ≥ 1% de escala completa 0 kPa ≤ p ≤ 0,345 MPa (0 psi ≤ p ≤ 50 psi) (incluye 5 puntos de calibración) | D12: Presión | E12: Procedimiento ME-003 para la calibración de manómetros, vacuómetros y manovacuómetros, Centro Español de Metrologia, Edición Digital 3, 2019. | F12: 6 | G12: 100000 | H12: =G12-(G12*0.15) -> 85000
C13: Manómetros analógicos y digitales Clase de exactitud ≥ 0,25% de escala completa 0,345 MPa < p ≤ 2,07 MPa (50 psi < p ≤ 300 psi) (incluye 5 puntos de calibración) | D13: Presión | E13: Procedimiento ME-003 para la calibración de manómetros, vacuómetros y manovacuómetros, Centro Español de Metrologia, Edición Digital 3, 2019. | F13: 7 | G13: 100000 | H13: =G13-(G13*0.15) -> 85000
C14: Esfigmomanómetros mecánicos no invasivos analógicos 0 kPa ≤ p ≤ 40 kPa (0 mmHg ≤ p ≤ 300 mmHg) (incluye 7 puntos de calibración) | D14: Presión | E14: OIML R148-2 Non-invasive non-automated sphygmomanometers, Edition 2020, Numerales 1 y 10. | F14: 8 | G14: 90000 | H14: =G14-(G14*0.15) -> 76500
B15: MASA | C15: Instrumentos de pesaje de funcionamiento no automático con d ≥ 0,01 mg 0 g < m ≤ 220 g (incluye 11 puntos de calibración) | D15: Masa | E15: Guía para la calibración de instrumentos para pesar de funcionamiento no automático, SIM MWG7/cg-01/v.00. 2009. | F15: 10 | G15: 220000 | H15: =G15-(G15*0.15) -> 187000
C16: Instrumentos de pesaje de funcionamiento no automático con d ≥ 10 mg 220 g < m ≤ 5 kg (incluye 11 puntos de calibración) | D16: Masa | E16: Guía para la calibración de instrumentos para pesar de funcionamiento no automático, SIM MWG7/cg-01/v.00. 2009. | F16: 11 | G16: 180000 | H16: =G16-(G16*0.15) -> 153000
C17: Instrumentos de pesaje de funcionamiento no automático con d ≥ 0,1 g 5 kg < m ≤ 300 kg (incluye 11 puntos de calibración) | D17: Masa | E17: Guía para la calibración de instrumentos para pesar de funcionamiento no automático, SIM MWG7/cg-01/v.00.2009 | F17: 12 | G17: 180000 | H17: =G17-(G17*0.15) -> 153000
B18: No Acreditado | C18: Agitadores de Mazzini | D18: Velocidad Angular (RPM) | E18: Procedimiento Interno | F18: 13 | G18: 115000 | H18: =G18-(G18*0.15) -> 97750
C19: Angiógrafo | D19: kV, tiempo, kV emitido | E19: Procedimiento Interno | F19: 14 | G19: $ 494.615 | H19: =G19-(G19*0.15) -> 420422.75
C20: Mamógrafo | D20: kV, tiempo, kV emitido | E20: Procedimiento Interno | F20: 15 | G20: $ 494.616 | H20: =G20-(G20*0.15) -> 420423.6
C21: Arco En C | D21: kV, tiempo, kV emitido | E21: Procedimiento Interno | F21: 16 | G21: $ 430.100 | H21: =G21-(G21*0.15) -> 365585
C22: Aspiradores De Vacío (Succionador) | D22: Presión Negativa. | E22: Procedimiento Interno | F22: 17 | G22: 135000 | H22: =G22-(G22*0.15) -> 114750
C23: Pulsoxímetro O Monitor De Saturación De Oxigeno | D23: % SpO2 - Frecuencia Cardíaca. | E23: Procedimiento Interno | F23: 18 | G23: 80000 | H23: =G23-(G23*0.15) -> 68000
C24: Banda de esfuerzo | D24: Frecuencia Cardíaca - NIBP- % SpO2 | E24: Procedimiento Interno | F24: 19 | G24: 120000 | H24: =G24-(G24*0.15) -> 102000
C25: Baño Serológico - Baño de Maria | D25: Temperatura (4 puntos) | E25: Procedimiento Interno | F25: 20 | G25: 110000 | H25: =G25-(G25*0.15) -> 93500
C26: Blender | D26: Concentración de O2 | E26: Procedimiento Interno | F26: 21 | G26: 106950 | H26: =G26-(G26*0.15) -> 90907.5
C27: Bomba de infusión | D27: Volumen - Flujo | E27: Procedimiento Interno | F27: 22 | G27: 135000 | H27: =G27-(G27*0.15) -> 114750
C28: Calentador de Liquidos | D28: Temperatura | E28: Procedimiento Interno | F28: 23 | G28: $ 106.950 | H28: =G28-(G28*0.15) -> 90907.5
C29: Calefactor de manta térmica | D29: Temperatura | E29: Procedimiento Interno | F29: 24 | G29: $ 106.951 | H29: =G29-(G29*0.15) -> 90908.35
C30: Criostato | D30: Temperatura | E30: Procedimiento Interno | F30: 25 | G30: 220000 | H30: =G30-(G30*0.15) -> 187000
C31: Capnógrafo | D31: CO2 - %SpO2 | E31: Procedimiento Interno | F31: 26 | G31: 177439.56 | H31: =G31-(G31*0.15) -> 150823.63
C32: Amalgamador | D32: Revoluciones por minuto( RPM) | E32: Procedimiento Interno | F32: 27 | G32: 115000 | H32: =G32-(G32*0.15) -> 97750
C33: Centrífuga - Microcentrifuga | D33: Velocidad Angular (RPM) | E33: Procedimiento Interno | F33: 28 | G33: 115000 | H33: =G33-(G33*0.15) -> 97750
C34: Compresor Vascular - Presoterapia | D34: Presión. | E34: Procedimiento Interno | F34: 29 | G34: 135700 | H34: =G34-(G34*0.15) -> 115345
C35: Concentradores de oxígeno | D35: % de O2 | E35: Procedimiento Interno | F35: 30 | G35: 130000 | H35: =G35-(G35*0.15) -> 110500
C36: Densitómetros | D36: kV, tiempo, kV emitido | E36: Procedimiento Interno | F36: 31 | G36: $ 430.100 | H36: =G36-(G36*0.15) -> 365585
C37: Descongelador de Plasma | D37: Temperatura | E37: Procedimiento Interno | F37: 32 | G37: 220000 | H37: =G37-(G37*0.15) -> 187000
C38: Desfibrilador Automático DEA | D38: Energía, Voltajes, Corrientes, Tiempos, TILT, T50-T10 | E38: Procedimiento Interno | F38: 33 | G38: 190000 | H38: =G38-(G38*0.15) -> 161500
C39: Desfibrilador Automático DEA pulsado | D39: Energía, Voltajes, Corrientes, Tiempos, TILT, T50-T10 | E39: Procedimiento Interno | F39: 34 | G39: 190000 | H39: =G39-(G39*0.15) -> 161500
C40: Desfibrilador Bifásico | D40: Frecuencia Cardiaca, Energía, Voltajes, Corrientes, Tiempos de sincronia, TILT, T50-T10 | E40: Procedimiento Interno | F40: 35 | G40: 220000 | H40: =G40-(G40*0.15) -> 187000
C41: Desfibrilador con monitor de Signos vitales | D41: Frecuencia Cardiaca, SpO2,NIBP, Energía, Voltajes, Corrientes, Tiempos de sincronia, TILT, T50-T10 | E41: Procedimiento Interno | F41: 36 | G41: 270000 | H41: =G41-(G41*0.15) -> 229500
C42: Doppler Fetal | D42: Frecuencia cardíaca fetal | E42: Procedimiento Interno | F42: 37 | G42: 135000 | H42: =G42-(G42*0.15) -> 114750
C43: Ecógrafo | D43: Longitud Vertical - Horizontal y área | E43: Procedimiento Interno | F43: 38 | G43: 500000 | H43: =G43-(G43*0.15) -> 425000
C44: Electrobisturí | D44: Voltaje, Factor de Cresta, Ancho de Banda, Fugas de Af. | E44: Procedimiento Interno | F44: 39 | G44: 250000 | H44: =G44-(G44*0.15) -> 212500
C45: Electromiógrafo | D45: Frecuencia, Voltaje e Impedancia | E45: Procedimiento Interno | F45: 40 | G45: 190000 | H45: =G45-(G45*0.15) -> 161500
C46: Electrocardiógrafo | D46: Frecuencia y Amplitud | E46: Procedimiento Interno | F46: 41 | G46: 172000 | H46: =G46-(G46*0.15) -> 146200
C47: Electrocauterio | D47: Voltaje, Factor de Cresta, Ancho de Banda, Fugas de Af | E47: Procedimiento Interno | F47: 42 | G47: $ 172.500 | H47: =G47-(G47*0.15) -> 146625
C48: Equipo de presión negativa para tratamiento de heridas | D48: Presión | E48: Procedimiento Interno | F48: 43 | G48: 115000 | H48: =G48-(G48*0.15) -> 97750
C49: Equipo de alto flujo | D49: Flujo | E49: Procedimiento Interno | F49: 44 | G49: 120000 | H49: =G49-(G49*0.15) -> 102000
C50: Equipos Para Detartraje (Cavitración, neumática, magnetostrictiva y/o piezoeléctrica, escaler) | D50: Amplitud y Frecuencia | E50: Procedimiento Interno | F50: 45 | G50: 172500 | H50: =G50-(G50*0.15) -> 146625
C51: Hydrocolector | D51: Temperatura | E51: Procedimiento Interno | F51: 46 | G51: 106951 | H51: =G51-(G51*0.15) -> 90908.35
C52: Equipos para terapia fisica TENS - EMS - 2 Canales | D52: Frecuencia y amplitud | E52: Procedimiento Interno | F52: 47 | G52: 172500 | H52: =G52-(G52*0.15) -> 146625
C53: Equipos para terapia fisica TENS - EMS (Neuroestimulador) - 1 Canal | D53: Frecuencia y amplitud | E53: Procedimiento Interno | F53: 48 | G53: 125000 | H53: =G53-(G53*0.15) -> 106250
C54: Equipos de test de Holter por grabadora ECG | D54: Frecuencia y amplitud | E54: Procedimiento Interno | F54: 50 | G54: 150000 | H54: =G54-(G54*0.15) -> 127500
C55: Equipos de test de presurometría ambulatoria grabadora | D55: Presión NIBP y Frecuencia | E55: Procedimiento Interno | F55: 51 | G55: 135700 | H55: =G55-(G55*0.15) -> 115345
C56: Esterilzador a vapor, Óxido de Etileno, | D56: Servicio de validación a (esterilizador oxido de etileno, IQ, OQ, PQ, 4 ciclos preferiblemente 1 sin carga y 3 con carga, 5 sensores de temp, 1 sensor de presión,) | E56: Validación | F56: 52 | G56: 500000 | H56: =G56-(G56*0.15) -> 425000
C57: Estimulador Nervioso/ muscular | D57: Frecuencia y amplitud | E57: Procedimiento Interno | F57: 53 | G57: 125000 | H57: =G57-(G57*0.15) -> 106250
C58: Flujometros (Regulador de oxígeno) | D58: Flujo | E58: Procedimiento Interno | F58: 54 | G58: 80000 | H58: =G58-(G58*0.15) -> 68000
C59: Flujometro Doble | D59: Flujo | E59: Procedimiento Interno | F59: 55 | G59: 145000 | H59: =G59-(G59*0.15) -> 123250
C60: Fluoroscopio | D60: kV, tiempo, kV emitido | E60: Procedimiento Interno | F60: 56 | G60: $ 430.100 | H60: =G60-(G60*0.15) -> 365585
C61: Humidificador Vía Aérea | D61: Temperatura en vía ( 2 Puntos) | E61: Procedimiento Interno | F61: 58 | G61: 106950 | H61: =G61-(G61*0.15) -> 90907.5
C62: Incubadora Biológica | D62: Temperatura | E62: Procedimiento Interno | F62: 59 | G62: 115000 | H62: =G62-(G62*0.15) -> 97750
C63: Incubadora Neonatal / Incubadora De Transporte | D63: Temperatura (Uniformidad, estabilidad en el tiempo, Ruido, Humedad Relativa, Flujo. | E63: Procedimiento Interno | F63: 60 | G63: 287334.07 | H63: =G63-(G63*0.15) -> 244233.96
C64: Nebulizador | D64: Presión- Flujo | E64: Procedimiento Interno | F64: 61 | G64: 120750 | H64: =G64-(G64*0.15) -> 102637.5
C65: Insuflador De CO2 | D65: Presión- Flujo | E65: Procedimiento Interno | F65: 62 | G65: 172500 | H65: =G65-(G65*0.15) -> 146625
C66: Inyector de medio de contraste | D66: Presión- Flujo | E66: Procedimiento Interno | F66: 63 | G66: 286350 | H66: =G66-(G66*0.15) -> 243397.5
C67: Espirómetro | D67: Volumen - Flujo | E67: Procedimiento Interno | F67: 64 | G67: 180000 | H67: =G67-(G67*0.15) -> 153000
C68: Cuna De Calor Radiante | D68: Temperatura | E68: Procedimiento Interno | F68: 66 | G68: $ 172.500 | H68: =G68-(G68*0.15) -> 146625
C69: Lámparas De Fotocurado | D69: mW/cm2 | E69: Procedimiento Interno | F69: 67 | G69: 115000 | H69: =G69-(G69*0.15) -> 97750
C70: Lámpara De Fototerapia | D70: μw/Cm2 | E70: Procedimiento Interno | F70: 68 | G70: $ 172.500 | H70: =G70-(G70*0.15) -> 146625
C71: Lipoescultores | D71: Presión De Vacío | E71: Procedimiento Interno | F71: 69 | G71: 135000 | H71: =G71-(G71*0.15) -> 114750
C72: Máquina De Anestesia (Sin Vaporizadores) (Incluido Ventilador) | D72: Volumen - Tiempo - Frecuencia - Presión – Flujo. | E72: Procedimiento Interno | F72: 70 | G72: 458000 | H72: =G72-(G72*0.15) -> 389300
C73: Marcapasos Externos | D73: Frecuencia, Sensibilidad ,Ancho De Pulso. | E73: Procedimiento Interno | F73: 72 | G73: 195000 | H73: =G73-(G73*0.15) -> 165750
C74: Monitor multiparamétrico (10 Variables) | D74: Frecuencia Cardíaca - %SpO2 - NIBP - Temperatura, Frecuencia Respiratoria-Gasto Cardíaco- Presión Invasiva (IBP) ,CO2, (8 a 10 Variables) | E74: Procedimiento Interno | F74: 73 | G74: 256000 | H74: =G74-(G74*0.15) -> 217600
C75: Monitor de Signos Vitales (De 3 a 5 Variables) | D75: Frecuencia , %SpO2, NIBP, Temperatura o Frecuencia respiratoria (3 a 5 Variables) | E75: Procedimiento Interno | F75: 77 | G75: 180000 | H75: =G75-(G75*0.15) -> 153000
C76: Monitor de Signos Vitales ( De 5 a 7 Variables) | D76: Frecuencia Cardíaca - %SpO2 - NIBP - Temperatura, Frecuencia Respiratoria, Presión Invasiva (IBP) ( 5 a 7 Variables) | E76: Procedimiento Interno | F76: 78 | G76: 220000 | H76: =G76-(G76*0.15) -> 187000
C77: Pulsiometro - Monitor de Oxígeno (Oximetro) | D77: %SpO2 | E77: Procedimiento Interno | F77: 79 | G77: 85000 | H77: =G77-(G77*0.15) -> 72250
C78: Monitor Fetal | D78: Fetocardia y Nivel de Contracción Uterina | E78: Procedimiento Interno | F78: 81 | G78: 220000 | H78: =G78-(G78*0.15) -> 187000
C79: Nevera Farmacéutica | D79: Servicio de validación a (nevera farmacéutica 1 puerta, muestreo por 24 horas, IQ, OQ PQ, 5 sensores temp, test de puerta abierta, test de desconexión, test de recuperación,) | E79: Validación | F79: 82 | G79: 339892.31 | H79: =G79-(G79*0.15) -> 288908.46
C80: Neumoinsuflador | D80: Flujo y Presión | E80: Procedimiento Interno | F80: 83 | G80: 172500 | H80: =G80-(G80*0.15) -> 146625
C81: Neumotaponador | D81: Presión | E81: Procedimiento Interno | F81: 84 | G81: 120000 | H81: =G81-(G81*0.15) -> 102000
C82: Planchas de calentamiento | D82: Velocidad Angular RPM y Temperatura | E82: Procedimiento Interno | F82: 85 | G82: 90000 | H82: =G82-(G82*0.15) -> 76500
C83: Panorámicos | D83: kV, tiempo, kV emitido | E83: Procedimiento Interno | F83: 86 | G83: 350000 | H83: =G83-(G83*0.15) -> 297500
C84: Equipo de Rayos X - Arco en C - Fluroscopio. | D84: kV, tiempo, kV emitido | E84: Procedimiento Interno | F84: 89 | G84: $ 430.100 | H84: =G84-(G84*0.15) -> 365585
C85: Peri Apicales | D85: kV, tiempo, kV emitido | E85: Procedimiento Interno | F85: 90 | G85: 350000 | H85: =G85-(G85*0.15) -> 297500
C86: Prueba de Seguridad Eléctrica | D86: Voltajes, Corrientes, Resistencia. | E86: Procedimiento Interno | F86: 91 | G86: 115000 | H86: =G86-(G86*0.15) -> 97750
C87: Desfibrilador monofásico | D87: Frecuencia Cardíaca, Energía, Voltajes, Corrientes, Tiempos de sincronía, TILT, T50-T10 | E87: Procedimiento Interno | F87: 92 | G87: 180000 | H87: =G87-(G87*0.15) -> 153000
C88: Consola de Contrapulsación | D88: Presión invasiva estática , Frecuencia Cardíaca | E88: Procedimiento Interno | F88: 93 | G88: 190000 | H88: =G88-(G88*0.15) -> 161500
C89: Regulador de Presión | D89: Presión | E89: Procedimiento Interno | F89: 94 | G89: 106953 | H89: =G89-(G89*0.15) -> 90910.05
C90: Shaver para artroscopia | D90: Velocidad Angular RPM y Flujo | E90: Procedimiento Interno | F90: 95 | G90: 215050 | H90: =G90-(G90*0.15) -> 182792.5
C91: Surgybone | D91: Seguridad eléctrica | E91: Procedimiento Interno | F91: 96 | G91: 125000 | H91: =G91-(G91*0.15) -> 106250
C92: Tensiómetro Automático | D92: Presión y Frecuencia Cardíaca. | E92: Procedimiento Interno | F92: 97 | G92: 80000 | H92: =G92-(G92*0.15) -> 68000
C93: Tonómetro | D93: Peso Vs. Presión | E93: Procedimiento Interno | F93: 98 | G93: 190000 | H93: =G93-(G93*0.15) -> 161500
C94: Ultrasonido de fisioterapia (Unidad de electroterapia) | D94: Potencia W | E94: Procedimiento Interno | F94: 99 | G94: 195000 | H94: =G94-(G94*0.15) -> 165750
C95: Vacuómetros - Regulador de Vacío | D95: Presión Negativa. | E95: Procedimiento Interno | F95: 101 | G95: 115000 | H95: =G95-(G95*0.15) -> 97750
C96: Esterilizador de vapor | D96: 1 Temperatura, IQ, OQ, PQ, 1 Ciclo Vacío, 3 Ciclos con Carga, 5 Sensores Temperatura y 1 Presión | E96: Validación | F96: 102 | G96: 382894.51 | H96: =G96-(G96*0.15) -> 325460.33
... C105: Ventiladores Mecánicos de alta Frecuencia | D105: Volumen -Frecuencia Respiratoria -Presiónes- Flujo-Tiempo y FiO2 | E105: Procedimiento Interno | F105: 114 | G105: 380000 | H105: =G105-(G105*0.15) -> 323000
